Fivepaisa_modular/__init__.py
Fivepaisa_modular/auto_sqoff.py
Fivepaisa_modular/buyside_sqoff.py
Fivepaisa_modular/create_log.py
Fivepaisa_modular/df_strike_gen.py
Fivepaisa_modular/inputs.py
Fivepaisa_modular/logging_funcs.py
Fivepaisa_modular/login.py
Fivepaisa_modular/order_place.py
Fivepaisa_modular/pip_installs.py
Fivepaisa_modular/scripmaster_download.py
Fivepaisa_modular/sl_monitoring.py
Fivepaisa_modular/stoploss_place.py
Fivepaisa_modular-0.0.23.dist-info/LICENCE.txt
Fivepaisa_modular-0.0.23.dist-info/METADATA
Fivepaisa_modular-0.0.23.dist-info/WHEEL
Fivepaisa_modular-0.0.23.dist-info/top_level.txt
Fivepaisa_modular-0.0.23.dist-info/RECORD
