Metadata-Version: 2.1
Name: Fivepaisa-modular
Version: 0.0.23
Summary: For generating df_strike_price dataframe
Home-page: https://pypi.org/project/df-strike-tut/
Author: Denny Babu
Author-email: dannibabup@gmail.com
Classifier: Programming Language :: Python :: 3
Classifier: License :: OSI Approved :: MIT License
Classifier: Operating System :: OS Independent
Requires-Python: >=3.7
License-File: LICENCE.txt
